mcp_server/__init__.py
mcp_server/example.py
mcp_server/example_client.py
mcp_server/main.py
mcp_server/token_manager.py
ttmoc/__init__.py
ttmoc/__main__.py
ttmoc/cli.py
ttmoc-0.1.9.dist-info/METADATA
ttmoc-0.1.9.dist-info/WHEEL
ttmoc-0.1.9.dist-info/entry_points.txt
ttmoc-0.1.9.dist-info/top_level.txt
ttmoc-0.1.9.dist-info/RECORD
