Metadata-Version: 2.4
Name: ttmoc
Version: 0.1.9
Summary: Talk-To-My-Org-Chart: CLI MCP server for org chart queries.
Author: ttthree
Author-email: ttthree <ttthree@gmail.com>
Requires-Python: >=3.8
Requires-Dist: requests
Requires-Dist: pydantic
Requires-Dist: azure-identity
Requires-Dist: mcp
Requires-Dist: python-dotenv
Requires-Dist: httpx
Dynamic: author
Dynamic: requires-python
